{
    "parent": "amazia:village/root",
    "criteria": {
        "make_bard": {
            "conditions": {
                "item": "amazia:enchanter_transformation_token"
            },
            "trigger": "minecraft:using_item"
        }
    },
    "display": {
        "announce_to_chat": true,
        "description": {
            "translate": "advancements.village.enchanter.description"
        },
        "frame": "goal",
        "icon": {
            "item": "amazia:enchanter_transformation_token"
        },
        "show_toast": true,
        "title": {
            "translate": "advancements.village.enchanter.title"
        }
    },
    "rewards": {
        "experience": 85
    }
}